task1/counter.sv
module counter #(
    parameter WIDTH = 8
) (
    // interface signals
    input logic clk,
    input logic rst,
    input logic en,
    output logic [WIDTH-1 : 0] count
);

always_ff @(posedge clk)
    if (rst) count <= {WIDTH{1'b0}};
    else count <= count + {{WIDTH-1{1'b0}}, en};

endmodule

task1/counter.vcd
$version Generated by VerilatedVcd $end
$date Thu Oct 10 20:43:34 2024 $end
$timescale 1ps $end

 $scope module TOP $end
  $var wire  1 # clk $end
  $var wire  8 & count [7:0] $end
  $var wire  1 % en $end
  $var wire  1 $ rst $end
  $scope module counter $end
   $var wire 32 ' WIDTH [31:0] $end
   $var wire  1 # clk $end
   $var wire  8 & count [7:0] $end
   $var wire  1 % en $end
   $var wire  1 $ rst $end
  $upscope $end
 $upscope $end
$enddefinitions $end


#0
1#
1$
0%
b00000000 &
b00000000000000000000000000001000 '
#1
0#
#2
1#
#3
0#
#4
1#
#5
0#
#6
1#
0$
#7
0#
#8
1#
#9
0#
#10
1#
#11
0#
#12
1#
1%
#13
0#
#14
1#
b00000001 &
#15
0#
#16
1#
b00000010 &
#17
0#
#18
1#
b00000011 &
#19
0#
#20
1#
b00000100 &
#21
0#
#22
1#
b00000101 &
#23
0#
#24
1#
b00000110 &
#25
0#
#26
1#
b00000111 &
#27
0#
#28
1#
b00001000 &
#29
0#
#30
1#
0%
b00001001 &
#31
0#
#32
1#
#33
0#
#36
1#
1%
#37
0#
#38
1#
b00001010 &
#39
0#
#40
1#
b00001011 &
#41
0#
#42
1#
b00001100 &
#43
0#
#44
1#
b00001101 &
#45
0#
#46
1#
b00001110 &
#47
0#
#48
1#
b00001111 &
#49
0#
#50
1#
b00010000 &
#51
0#
#52
1#
b00010001 &
#53
0#
#54
1#
b00010010 &
#55
0#
#56
1#
b00010011 &
#57
0#
#58
1#
b00010100 &
#59
0#
#60
1#
b00010101 &
#61
0#
#62
1#
1$
b00010110 &
#63
0#
#64
1#
0$
b00000000 &
#65
0#
#66
1#
b00000001 &
#67
0#
#68
1#
b00000010 &
#69
0#
#70
1#
b00000011 &
#71
0#
#72
1#
b00000100 &
#73
0#
#74
1#
b00000101 &
#75
0#
#76
1#
b00000110 &
#77
0#
#78
1#
b00000111 &
#79
0#
#80
1#
b00001000 &
#81
0#
#82
1#
0%
b00001001 &
#83
0#
#84
1#
#85
0#
#88
1#
1%
#89
0#
#90
1#
b00001010 &
#91
0#
#92
1#
b00001011 &
#93
0#
#94
1#
b00001100 &
#95
0#
#96
1#
b00001101 &
#97
0#
#98
1#
b00001110 &
#99
0#
#100
1#
b00001111 &
#101
0#
#102
1#
b00010000 &
#103
0#
#104
1#
b00010001 &
#105
0#
#106
1#
b00010010 &
#107
0#
#108
1#
b00010011 &
#109
0#
#110
1#
b00010100 &
#111
0#
#112
1#
b00010101 &
#113
0#
#114
1#
b00010110 &
#115
0#
#116
1#
b00010111 &
#117
0#
#118
1#
b00011000 &
#119
0#
#120
1#
b00011001 &
#121
0#
#122
1#
b00011010 &
#123
0#
#124
1#
b00011011 &
#125
0#
#126
1#
b00011100 &
#127
0#
#128
1#
b00011101 &
#129
0#
#130
1#
b00011110 &
#131
0#
#132
1#
b00011111 &
#133
0#
#134
1#
b00100000 &
#135
0#
#136
1#
b00100001 &
#137
0#
#138
1#
b00100010 &
#139
0#
#140
1#
b00100011 &
#141
0#
#142
1#
b00100100 &
#143
0#
#144
1#
b00100101 &
#145
0#
#146
1#
b00100110 &
#147
0#
#148
1#
b00100111 &
#149
0#
#150
1#
b00101000 &
#151
0#
#152
1#
b00101001 &
#153
0#
#154
1#
b00101010 &
#155
0#
#156
1#
b00101011 &
#157
0#
#158
1#
b00101100 &
#159
0#
#160
1#
b00101101 &
#161
0#
#162
1#
b00101110 &
#163
0#
#164
1#
b00101111 &
#165
0#
#166
1#
b00110000 &
#167
0#
#168
1#
b00110001 &
#169
0#
#170
1#
b00110010 &
#171
0#
#172
1#
b00110011 &
#173
0#
#174
1#
b00110100 &
#175
0#
#176
1#
b00110101 &
#177
0#
#178
1#
b00110110 &
#179
0#
#180
1#
b00110111 &
#181
0#
#182
1#
b00111000 &
#183
0#
#184
1#
b00111001 &
#185
0#
#186
1#
b00111010 &
#187
0#
#188
1#
b00111011 &
#189
0#
#190
1#
b00111100 &
#191
0#
#192
1#
b00111101 &
#193
0#
#194
1#
b00111110 &
#195
0#
#196
1#
b00111111 &
#197
0#
#198
1#
b01000000 &
#199
0#
#200
1#
b01000001 &
#201
0#
#202
1#
b01000010 &
#203
0#
#204
1#
b01000011 &
#205
0#
#206
1#
b01000100 &
#207
0#
#208
1#
b01000101 &
#209
0#
#210
1#
b01000110 &
#211
0#
#212
1#
b01000111 &
#213
0#
#214
1#
b01001000 &
#215
0#
#216
1#
b01001001 &
#217
0#
#218
1#
b01001010 &
#219
0#
#220
1#
b01001011 &
#221
0#
#222
1#
b01001100 &
#223
0#
#224
1#
b01001101 &
#225
0#
#226
1#
b01001110 &
#227
0#
#228
1#
b01001111 &
#229
0#
#230
1#
b01010000 &
#231
0#
#232
1#
b01010001 &
#233
0#
#234
1#
b01010010 &
#235
0#
#236
1#
b01010011 &
#237
0#
#238
1#
b01010100 &
#239
0#
#240
1#
b01010101 &
#241
0#
#242
1#
b01010110 &
#243
0#
#244
1#
b01010111 &
#245
0#
#246
1#
b01011000 &
#247
0#
#248
1#
b01011001 &
#249
0#
#250
1#
b01011010 &
#251
0#
#252
1#
b01011011 &
#253
0#
#254
1#
b01011100 &
#255
0#
#256
1#
b01011101 &
#257
0#
#258
1#
b01011110 &
#259
0#
#260
1#
b01011111 &
#261
0#
#262
1#
b01100000 &
#263
0#
#264
1#
b01100001 &
#265
0#
#266
1#
b01100010 &
#267
0#
#268
1#
b01100011 &
#269
0#
#270
1#
b01100100 &
#271
0#
#272
1#
b01100101 &
#273
0#
#274
1#
b01100110 &
#275
0#
#276
1#
b01100111 &
#277
0#
#278
1#
b01101000 &
#279
0#
#280
1#
b01101001 &
#281
0#
#282
1#
b01101010 &
#283
0#
#284
1#
b01101011 &
#285
0#
#286
1#
b01101100 &
#287
0#
#288
1#
b01101101 &
#289
0#
#290
1#
b01101110 &
#291
0#
#292
1#
b01101111 &
#293
0#
#294
1#
b01110000 &
#295
0#
#296
1#
b01110001 &
#297
0#
#298
1#
b01110010 &
#299
0#
#300
1#
b01110011 &
#301
0#
#302
1#
b01110100 &
#303
0#
#304
1#
b01110101 &
#305
0#
#306
1#
b01110110 &
#307
0#
#308
1#
b01110111 &
#309
0#
#310
1#
b01111000 &
#311
0#
#312
1#
b01111001 &
#313
0#
#314
1#
b01111010 &
#315
0#
#316
1#
b01111011 &
#317
0#
#318
1#
b01111100 &
#319
0#
#320
1#
b01111101 &
#321
0#
#322
1#
b01111110 &
#323
0#
#324
1#
b01111111 &
#325
0#
#326
1#
b10000000 &
#327
0#
#328
1#
b10000001 &
#329
0#
#330
1#
b10000010 &
#331
0#
#332
1#
b10000011 &
#333
0#
#334
1#
b10000100 &
#335
0#
#336
1#
b10000101 &
#337
0#
#338
1#
b10000110 &
#339
0#
#340
1#
b10000111 &
#341
0#
#342
1#
b10001000 &
#343
0#
#344
1#
b10001001 &
#345
0#
#346
1#
b10001010 &
#347
0#
#348
1#
b10001011 &
#349
0#
#350
1#
b10001100 &
#351
0#
#352
1#
b10001101 &
#353
0#
#354
1#
b10001110 &
#355
0#
#356
1#
b10001111 &
#357
0#
#358
1#
b10010000 &
#359
0#
#360
1#
b10010001 &
#361
0#
#362
1#
b10010010 &
#363
0#
#364
1#
b10010011 &
#365
0#
#366
1#
b10010100 &
#367
0#
#368
1#
b10010101 &
#369
0#
#370
1#
b10010110 &
#371
0#
#372
1#
b10010111 &
#373
0#
#374
1#
b10011000 &
#375
0#
#376
1#
b10011001 &
#377
0#
#378
1#
b10011010 &
#379
0#
#380
1#
b10011011 &
#381
0#
#382
1#
b10011100 &
#383
0#
#384
1#
b10011101 &
#385
0#
#386
1#
b10011110 &
#387
0#
#388
1#
b10011111 &
#389
0#
#390
1#
b10100000 &
#391
0#
#392
1#
b10100001 &
#393
0#
#394
1#
b10100010 &
#395
0#
#396
1#
b10100011 &
#397
0#
#398
1#
b10100100 &
#399
0#
#400
1#
b10100101 &
#401
0#
#402
1#
b10100110 &
#403
0#
#404
1#
b10100111 &
#405
0#
#406
1#
b10101000 &
#407
0#
#408
1#
b10101001 &
#409
0#
#410
1#
b10101010 &
#411
0#
#412
1#
b10101011 &
#413
0#
#414
1#
b10101100 &
#415
0#
#416
1#
b10101101 &
#417
0#
#418
1#
b10101110 &
#419
0#
#420
1#
b10101111 &
#421
0#
#422
1#
b10110000 &
#423
0#
#424
1#
b10110001 &
#425
0#
#426
1#
b10110010 &
#427
0#
#428
1#
b10110011 &
#429
0#
#430
1#
b10110100 &
#431
0#
#432
1#
b10110101 &
#433
0#
#434
1#
b10110110 &
#435
0#
#436
1#
b10110111 &
#437
0#
#438
1#
b10111000 &
#439
0#
#440
1#
b10111001 &
#441
0#
#442
1#
b10111010 &
#443
0#
#444
1#
b10111011 &
#445
0#
#446
1#
b10111100 &
#447
0#
#448
1#
b10111101 &
#449
0#
#450
1#
b10111110 &
#451
0#
#452
1#
b10111111 &
#453
0#
#454
1#
b11000000 &
#455
0#
#456
1#
b11000001 &
#457
0#
#458
1#
b11000010 &
#459
0#
#460
1#
b11000011 &
#461
0#
#462
1#
b11000100 &
#463
0#
#464
1#
b11000101 &
#465
0#
#466
1#
b11000110 &
#467
0#
#468
1#
b11000111 &
#469
0#
#470
1#
b11001000 &
#471
0#
#472
1#
b11001001 &
#473
0#
#474
1#
b11001010 &
#475
0#
#476
1#
b11001011 &
#477
0#
#478
1#
b11001100 &
#479
0#
#480
1#
b11001101 &
#481
0#
#482
1#
b11001110 &
#483
0#
#484
1#
b11001111 &
#485
0#
#486
1#
b11010000 &
#487
0#
#488
1#
b11010001 &
#489
0#
#490
1#
b11010010 &
#491
0#
#492
1#
b11010011 &
#493
0#
#494
1#
b11010100 &
#495
0#
#496
1#
b11010101 &
#497
0#
#498
1#
b11010110 &
#499
0#
#500
1#
b11010111 &
#501
0#
#502
1#
b11011000 &
#503
0#
#504
1#
b11011001 &
#505
0#
#506
1#
b11011010 &
#507
0#
#508
1#
b11011011 &
#509
0#
#510
1#
b11011100 &
#511
0#
#512
1#
b11011101 &
#513
0#
#514
1#
b11011110 &
#515
0#
#516
1#
b11011111 &
#517
0#
#518
1#
b11100000 &
#519
0#
#520
1#
b11100001 &
#521
0#
#522
1#
b11100010 &
#523
0#
#524
1#
b11100011 &
#525
0#
#526
1#
b11100100 &
#527
0#
#528
1#
b11100101 &
#529
0#
#530
1#
b11100110 &
#531
0#
#532
1#
b11100111 &
#533
0#
#534
1#
b11101000 &
#535
0#
#536
1#
b11101001 &
#537
0#
#538
1#
b11101010 &
#539
0#
#540
1#
b11101011 &
#541
0#
#542
1#
b11101100 &
#543
0#
#544
1#
b11101101 &
#545
0#
#546
1#
b11101110 &
#547
0#
#548
1#
b11101111 &
#549
0#
#550
1#
b11110000 &
#551
0#
#552
1#
b11110001 &
#553
0#
#554
1#
b11110010 &
#555
0#
#556
1#
b11110011 &
#557
0#
#558
1#
b11110100 &
#559
0#
#560
1#
b11110101 &
#561
0#
#562
1#
b11110110 &
#563
0#
#564
1#
b11110111 &
#565
0#
#566
1#
b11111000 &
#567
0#
#568
1#
b11111001 &
#569
0#
#570
1#
b11111010 &
#571
0#
#572
1#
b11111011 &
#573
0#
#574
1#
b11111100 &
#575
0#
#576
1#
b11111101 &
#577
0#
#578
1#
b11111110 &
#579
0#
#580
1#
b11111111 &
#581
0#
#582
1#
b00000000 &
#583
0#
#584
1#
b00000001 &
#585
0#
#586
1#
b00000010 &
#587
0#
#588
1#
b00000011 &
#589
0#
#590
1#
b00000100 &
#591
0#
#592
1#
b00000101 &
#593
0#
#594
1#
b00000110 &
#595
0#
#596
1#
b00000111 &
#597
0#
#598
1#
b00001000 &
#599
0#
#600
1#
0%
b00001001 &
